Workbook

Sheet Config
A1: KONFIGURASI GLOBAL — PROJECT RISK & HEALTH DASHBOARD
A2: Sheet ini adalah pusat pengaturan. Ubah nilai di kolom B untuk menyesuaikan seluruh dashboard (Excel & HTML).
A4: A. IDENTITAS PROYEK
A5: Parameter | B5: Nilai | C5: Keterangan
A6: Nama Perusahaan | B6: Test | C6: Nama lengkap perusahaan pemilik proyek
A7: Nama Proyek | B7: Satu | C7: Nama proyek yang dilaporkan
A8: Kapasitas Produksi | B8: 300.000 MTPY | C8: Kapasitas desain pabrik
A10: B. BOBOT 5 PILAR PROJECT HEALTH SCORE (PHS)
A11: Pilar Kesehatan | B11: Bobot | C11: Keterangan
A12: Financial Health | B12: 0.2 | C12: Berdasarkan CPI
A13: Schedule Health | B13: 0.2 | C13: Berdasarkan SPI
A14: Supply Readiness (SRI) | B14: 0.2 | C14: Indeks kesiapan pasokan bahan baku
A15: Project Execution (PEI) | B15: 0.2 | C15: Indeks pelaksanaan proyek fisik
A16: Commercial Readiness (CRI) | B16: 0.2 | C16: Indeks kesiapan komersial
A17: TOTAL BOBOT | B17: =SUM(B12:B16) -> 1 | C17: Harus = 1.00
A19: C. BOBOT OVERALL RISK INDEX
A20: Komponen Risiko | B20: Bobot | C20: Keterangan
A21: Supply Risk Index | B21: 0.4 | C21: Bahan baku, logistik
A22: Execution Risk Index | B22: 0.4 | C22: Engineering, procurement, construction
A23: Commercial Risk Index | B23: 0.2 | C23: Offtake, marketing, distribusi
A24: TOTAL BOBOT | B24: =SUM(B21:B23) -> 1
A26: D. PENGATURAN TAMPILAN DASHBOARD
A27: Parameter | B27: Nilai | C27: Keterangan
A28: Jumlah Executive Actions | B28: 5 | C28: Berapa prioritas action yang ditampilkan di slide
A29: EWS Buffer Toleransi (%) | B29: 10 | C29: Persentase buffer batas Waspada
A31: E. KUSTOMISASI WARNA (HEX CODE)
A32: Elemen | B32: Hex Code | C32: Preview
A33: Warna Hijau (Aman) | B33: #2E9B57 | C33: Preview
A34: Warna Kuning (Pantau) | B34: #E8B93A | C34: Preview
A35: Warna Oranye (Waspada) | B35: #E4622E | C35: Preview
A36: Warna Merah (Kritis) | B36: #C0392B | C36: Preview
A37: Warna Navy (Aksen) | B37: #0B1F3A | C37: Preview

Sheet Panduan
A1: PANDUAN PENGGUNAAN — PROJECT RISK & HEALTH DASHBOARD v3
A2: Versi 3.0 | Dibuat untuk memudahkan pelaporan risiko dan kesehatan proyek secara berkala.
A4: 1. PENDAHULUAN
A5: Dashboard ini dirancang untuk memantau kesehatan proyek melalui 5 pilar utama:
A6: a. Financial Health (CPI & SPI) — efisiensi biaya dan jadwal
A7: b. Supply Readiness Index (SRI) — kesiapan pasokan bahan baku
A8: c. Project Execution Index (PEI) — pelaksanaan proyek fisik
A9: d. Commercial Readiness Index (CRI) — kesiapan komersial
A10: e. Risk Index — profil risiko keseluruhan (benchmark Pertamina)
A12: 2. STRUKTUR FILE EXCEL
A13: Sheet | C13: Fungsi | F13: Siapa Mengisi
A14: Config | C14: Pengaturan global: nama proyek, bobot pilar, warna | F14: PM / PMO (sekali)
A15: Panduan | C15: Manual penggunaan (sheet ini) | F15: Hanya dibaca
A16: Referensi_Threshold | C16: Referensi formula, threshold, skala risiko | F16: Risk Manager (sekali)
A17: Input_Bulanan | C17: Input data utama setiap bulan | F17: Project Control (bulanan)
A18: Risk_Action_Tracker | C18: Tracker aksi mitigasi & keputusan Direksi | F18: Project Control (bulanan)
A19: Dashboard | C19: Ringkasan visual otomatis | F19: Otomatis
A21: 3. PANDUAN WARNA SEL
A22: KUNING (font biru) | B22: Isi data Anda di sini
A23: ABU-ABU | B23: Jangan diubah manual
A26: 4. MENAMBAH BARIS BARU (EWS / TOP RISK / ACTIONS)
A27: Untuk menambah parameter EWS atau Top Risk baru:
A28: a. Klik kanan pada baris TERAKHIR data di bagian tersebut
A29: b. Pilih 'Insert' -> 'Entire Row' untuk menyisipkan baris baru
A30: c. Salin formula dari baris di atas (khusus kolom formula/abu-abu)
A31: d. Isi data baru di kolom input (kuning)
A32: e. HTML importer akan otomatis mendeteksi baris baru saat import
A34: 5. MENGUBAH BOBOT
A35: a. Buka sheet 'Referensi_Threshold' untuk bobot SRI/PEI/CRI
A36: b. Ubah nilai bobot di kolom B
A37: c. Sheet 'Input_Bulanan' kolom E otomatis menyesuaikan
A38: 5. CARA MENGATUR PRIORITAS EXECUTIVE ACTIONS
... A48: f. Gunakan tombol Dark Mode untuk mode malam

Sheet Dashboard
B1: PROJECT RISK & HEALTH DASHBOARD - Proyek X PROJECT Perusahaan X (Perusahaan X)
B2: ="Reporting Period: "&TEXT(Input_Bulanan!D5, "mmmm yyyy")&" | Status: "&Input_Bulanan!F5&" | Dicetak: "&TEXT(TODAY(), "DD-MM-YYYY") -> Reporting Period: November 2026 | Status: Final | Dicetak: 23-07-2026
B4: PANEL A - PROJECT HEALTH OVERVIEW (Retrospective Performance) | M4: PANEL B - CURRENT RISK EXPOSURE (Prospective Threats)
B5: Overall Project Health Score (PHS) | G5: Sub-Index Readiness & Performance | M5: Overall Risk Level (Composite) | R5: Risk Profile Heat Map (Likelihood x Consequence)
B6: =((IF(Input_Bulanan!D12>=1,100,Input_Bulanan!D12*100)*0.2)+(IF(Input_Bulanan!D14>=1,100,Input_Bulanan!D14*100)*0.2)+(Input_Bulanan!D24*100*0.2)+(Input_Bulanan!D32*100*0.2)+(Input_Bulanan!D42*100*0.2))/100 -> 0.8386 | G6: Supply Readiness Index (SRI) | K6: =Input_Bulanan!D24 -> 0.805 | M6: =Input_Bulanan!D49 -> Moderate to High | R6: L=5 | S6: =IF(AND(Input_Bulanan!$G$75=1,Input_Bulanan!$F$75=5),Input_Bulanan!$C$75,IF(AND(Input_Bulanan!$G$76=1,Input_Bulanan!$F$76=5),Input_Bulanan!$C$76,IF(AND(Input_Bulanan!$G$77=1,Input_Bulanan!$F$77=5),Input_Bulanan!$C$77,IF(AND(Input_Bulanan!$G$78=1,Input_Bulanan!$F$78=5),Input_Bulanan!$C$78,"")))) | T6: =IF(AND(Input_Bulanan!$G$75=2,Input_Bulanan!$F$75=5),Input_Bulanan!$C$75,IF(AND(Input_Bulanan!$G$76=2,Input_Bulanan!$F$76=5),Input_Bulanan!$C$76,IF(AND(Input_Bulanan!$G$77=2,Input_Bulanan!$F$77=5),Input_Bulanan!$C$77,IF(AND(Input_Bulanan!$G$78=2,Input_Bulanan!$F$78=5),Input_Bulanan!$C$78,"")))) | U6: =IF(AND(Input_Bulanan!$G$75=3,Input_Bulanan!$F$75=5),Input_Bulanan!$C$75,IF(AND(Input_Bulanan!$G$76=3,Input_Bulanan!$F$76=5),Input_Bulanan!$C$76,IF(AND(Input_Bulanan!$G$77=3,Input_Bulanan!$F$77=5),Input_Bulanan!$C$77,IF(AND(Input_Bulanan!$G$78=3,Input_Bulanan!$F$78=5),Input_Bulanan!$C$78,"")))) | V6: =IF(AND(Input_Bulanan!$G$75=4,Input_Bulanan!$F$75=5),Input_Bulanan!$C$75,IF(AND(Input_Bulanan!$G$76=4,Input_Bulanan!$F$76=5),Input_Bulanan!$C$76,IF(AND(Input_Bulanan!$G$77=4,Input_Bulanan!$F$77=5),Input_Bulanan!$C$77,IF(AND(Input_Bulanan!$G$78=4,Input_Bulanan!$F$78=5),Input_Bulanan!$C$78,"")))) | W6: =IF(AND(Input_Bulanan!$G$75=5,Input_Bulanan!$F$75=5),Input_Bulanan!$C$75,IF(AND(Input_Bulanan!$G$76=5,Input_Bulanan!$F$76=5),Input_Bulanan!$C$76,IF(AND(Input_Bulanan!$G$77=5,Input_Bulanan!$F$77=5),Input_Bulanan!$C$77,IF(AND(Input_Bulanan!$G$78=5,Input_Bulanan!$F$78=5),Input_Bulanan!$C$78,"")))) -> C2
R7: L=4 | S7: =IF(AND(Input_Bulanan!$G$75=1,Input_Bulanan!$F$75=4),Input_Bulanan!$C$75,IF(AND(Input_Bulanan!$G$76=1,Input_Bulanan!$F$76=4),Input_Bulanan!$C$76,IF(AND(Input_Bulanan!$G$77=1,Input_Bulanan!$F$77=4),Input_Bulanan!$C$77,IF(AND(Input_Bulanan!$G$78=1,Input_Bulanan!$F$78=4),Input_Bulanan!$C$78,"")))) | T7: =IF(AND(Input_Bulanan!$G$75=2,Input_Bulanan!$F$75=4),Input_Bulanan!$C$75,IF(AND(Input_Bulanan!$G$76=2,Input_Bulanan!$F$76=4),Input_Bulanan!$C$76,IF(AND(Input_Bulanan!$G$77=2,Input_Bulanan!$F$77=4),Input_Bulanan!$C$77,IF(AND(Input_Bulanan!$G$78=2,Input_Bulanan!$F$78=4),Input_Bulanan!$C$78,"")))) | U7: =IF(AND(Input_Bulanan!$G$75=3,Input_Bulanan!$F$75=4),Input_Bulanan!$C$75,IF(AND(Input_Bulanan!$G$76=3,Input_Bulanan!$F$76=4),Input_Bulanan!$C$76,IF(AND(Input_Bulanan!$G$77=3,Input_Bulanan!$F$77=4),Input_Bulanan!$C$77,IF(AND(Input_Bulanan!$G$78=3,Input_Bulanan!$F$78=4),Input_Bulanan!$C$78,"")))) | V7: =IF(AND(Input_Bulanan!$G$75=4,Input_Bulanan!$F$75=4),Input_Bulanan!$C$75,IF(AND(Input_Bulanan!$G$76=4,Input_Bulanan!$F$76=4),Input_Bulanan!$C$76,IF(AND(Input_Bulanan!$G$77=4,Input_Bulanan!$F$77=4),Input_Bulanan!$C$77,IF(AND(Input_Bulanan!$G$78=4,Input_Bulanan!$F$78=4),Input_Bulanan!$C$78,"")))) -> C3 | W7: =IF(AND(Input_Bulanan!$G$75=5,Input_Bulanan!$F$75=4),Input_Bulanan!$C$75,IF(AND(Input_Bulanan!$G$76=5,Input_Bulanan!$F$76=4),Input_Bulanan!$C$76,IF(AND(Input_Bulanan!$G$77=5,Input_Bulanan!$F$77=4),Input_Bulanan!$C$77,IF(AND(Input_Bulanan!$G$78=5,Input_Bulanan!$F$78=4),Input_Bulanan!$C$78,"")))) -> C1
G8: Project Execution Index (PEI) | K8: =Input_Bulanan!D32 -> 0.768 | R8: L=3 | S8: =IF(AND(Input_Bulanan!$G$75=1,Input_Bulanan!$F$75=3),Input_Bulanan!$C$75,IF(AND(Input_Bulanan!$G$76=1,Input_Bulanan!$F$76=3),Input_Bulanan!$C$76,IF(AND(Input_Bulanan!$G$77=1,Input_Bulanan!$F$77=3),Input_Bulanan!$C$77,IF(AND(Input_Bulanan!$G$78=1,Input_Bulanan!$F$78=3),Input_Bulanan!$C$78,"")))) | T8: =IF(AND(Input_Bulanan!$G$75=2,Input_Bulanan!$F$75=3),Input_Bulanan!$C$75,IF(AND(Input_Bulanan!$G$76=2,Input_Bulanan!$F$76=3),Input_Bulanan!$C$76,IF(AND(Input_Bulanan!$G$77=2,Input_Bulanan!$F$77=3),Input_Bulanan!$C$77,IF(AND(Input_Bulanan!$G$78=2,Input_Bulanan!$F$78=3),Input_Bulanan!$C$78,"")))) | U8: =IF(AND(Input_Bulanan!$G$75=3,Input_Bulanan!$F$75=3),Input_Bulanan!$C$75,IF(AND(Input_Bulanan!$G$76=3,Input_Bulanan!$F$76=3),Input_Bulanan!$C$76,IF(AND(Input_Bulanan!$G$77=3,Input_Bulanan!$F$77=3),Input_Bulanan!$C$77,IF(AND(Input_Bulanan!$G$78=3,Input_Bulanan!$F$78=3),Input_Bulanan!$C$78,"")))) -> C4 | V8: =IF(AND(Input_Bulanan!$G$75=4,Input_Bulanan!$F$75=3),Input_Bulanan!$C$75,IF(AND(Input_Bulanan!$G$76=4,Input_Bulanan!$F$76=3),Input_Bulanan!$C$76,IF(AND(Input_Bulanan!$G$77=4,Input_Bulanan!$F$77=3),Input_Bulanan!$C$77,IF(AND(Input_Bulanan!$G$78=4,Input_Bulanan!$F$78=3),Input_Bulanan!$C$78,"")))) | W8: =IF(AND(Input_Bulanan!$G$75=5,Input_Bulanan!$F$75=3),Input_Bulanan!$C$75,IF(AND(Input_Bulanan!$G$76=5,Input_Bulanan!$F$76=3),Input_Bulanan!$C$76,IF(AND(Input_Bulanan!$G$77=5,Input_Bulanan!$F$77=3),Input_Bulanan!$C$77,IF(AND(Input_Bulanan!$G$78=5,Input_Bulanan!$F$78=3),Input_Bulanan!$C$78,""))))
R9: L=2 | S9: =IF(AND(Input_Bulanan!$G$75=1,Input_Bulanan!$F$75=2),Input_Bulanan!$C$75,IF(AND(Input_Bulanan!$G$76=1,Input_Bulanan!$F$76=2),Input_Bulanan!$C$76,IF(AND(Input_Bulanan!$G$77=1,Input_Bulanan!$F$77=2),Input_Bulanan!$C$77,IF(AND(Input_Bulanan!$G$78=1,Input_Bulanan!$F$78=2),Input_Bulanan!$C$78,"")))) | T9: =IF(AND(Input_Bulanan!$G$75=2,Input_Bulanan!$F$75=2),Input_Bulanan!$C$75,IF(AND(Input_Bulanan!$G$76=2,Input_Bulanan!$F$76=2),Input_Bulanan!$C$76,IF(AND(Input_Bulanan!$G$77=2,Input_Bulanan!$F$77=2),Input_Bulanan!$C$77,IF(AND(Input_Bulanan!$G$78=2,Input_Bulanan!$F$78=2),Input_Bulanan!$C$78,"")))) | U9: =IF(AND(Input_Bulanan!$G$75=3,Input_Bulanan!$F$75=2),Input_Bulanan!$C$75,IF(AND(Input_Bulanan!$G$76=3,Input_Bulanan!$F$76=2),Input_Bulanan!$C$76,IF(AND(Input_Bulanan!$G$77=3,Input_Bulanan!$F$77=2),Input_Bulanan!$C$77,IF(AND(Input_Bulanan!$G$78=3,Input_Bulanan!$F$78=2),Input_Bulanan!$C$78,"")))) | V9: =IF(AND(Input_Bulanan!$G$75=4,Input_Bulanan!$F$75=2),Input_Bulanan!$C$75,IF(AND(Input_Bulanan!$G$76=4,Input_Bulanan!$F$76=2),Input_Bulanan!$C$76,IF(AND(Input_Bulanan!$G$77=4,Input_Bulanan!$F$77=2),Input_Bulanan!$C$77,IF(AND(Input_Bulanan!$G$78=4,Input_Bulanan!$F$78=2),Input_Bulanan!$C$78,"")))) | W9: =IF(AND(Input_Bulanan!$G$75=5,Input_Bulanan!$F$75=2),Input_Bulanan!$C$75,IF(AND(Input_Bulanan!$G$76=5,Input_Bulanan!$F$76=2),Input_Bulanan!$C$76,IF(AND(Input_Bulanan!$G$77=5,Input_Bulanan!$F$77=2),Input_Bulanan!$C$77,IF(AND(Input_Bulanan!$G$78=5,Input_Bulanan!$F$78=2),Input_Bulanan!$C$78,""))))
B10: =IF(B6>=0.9,"HIJAU - SEHAT",IF(B6>=0.75,"KUNING - PANTAU",IF(B6>=0.6,"ORANYE - WASPADA","MERAH - KRITIS"))) -> KUNING - PANTAU | G10: Commercial Readiness Index (CRI) | K10: =Input_Bulanan!D42 -> 0.62 | M10: ="Skor Komposit: "&TEXT(Input_Bulanan!D48,"0,00")&" / 100" -> Skor Komposit: 75,32 / 100 | R10: L=1 | S10: =IF(AND(Input_Bulanan!$G$75=1,Input_Bulanan!$F$75=1),Input_Bulanan!$C$75,IF(AND(Input_Bulanan!$G$76=1,Input_Bulanan!$F$76=1),Input_Bulanan!$C$76,IF(AND(Input_Bulanan!$G$77=1,Input_Bulanan!$F$77=1),Input_Bulanan!$C$77,IF(AND(Input_Bulanan!$G$78=1,Input_Bulanan!$F$78=1),Input_Bulanan!$C$78,"")))) | T10: =IF(AND(Input_Bulanan!$G$75=2,Input_Bulanan!$F$75=1),Input_Bulanan!$C$75,IF(AND(Input_Bulanan!$G$76=2,Input_Bulanan!$F$76=1),Input_Bulanan!$C$76,IF(AND(Input_Bulanan!$G$77=2,Input_Bulanan!$F$77=1),Input_Bulanan!$C$77,IF(AND(Input_Bulanan!$G$78=2,Input_Bulanan!$F$78=1),Input_Bulanan!$C$78,"")))) | U10: =IF(AND(Input_Bulanan!$G$75=3,Input_Bulanan!$F$75=1),Input_Bulanan!$C$75,IF(AND(Input_Bulanan!$G$76=3,Input_Bulanan!$F$76=1),Input_Bulanan!$C$76,IF(AND(Input_Bulanan!$G$77=3,Input_Bulanan!$F$77=1),Input_Bulanan!$C$77,IF(AND(Input_Bulanan!$G$78=3,Input_Bulanan!$F$78=1),Input_Bulanan!$C$78,"")))) | V10: =IF(AND(Input_Bulanan!$G$75=4,Input_Bulanan!$F$75=1),Input_Bulanan!$C$75,IF(AND(Input_Bulanan!$G$76=4,Input_Bulanan!$F$76=1),Input_Bulanan!$C$76,IF(AND(Input_Bulanan!$G$77=4,Input_Bulanan!$F$77=1),Input_Bulanan!$C$77,IF(AND(Input_Bulanan!$G$78=4,Input_Bulanan!$F$78=1),Input_Bulanan!$C$78,"")))) | W10: =IF(AND(Input_Bulanan!$G$75=5,Input_Bulanan!$F$75=1),Input_Bulanan!$C$75,IF(AND(Input_Bulanan!$G$76=5,Input_Bulanan!$F$76=1),Input_Bulanan!$C$76,IF(AND(Input_Bulanan!$G$77=5,Input_Bulanan!$F$77=1),Input_Bulanan!$C$77,IF(AND(Input_Bulanan!$G$78=5,Input_Bulanan!$F$78=1),Input_Bulanan!$C$78,""))))
R11: C -> | S11: 1 | T11: 2 | U11: 3 | V11: 4 | W11: 5
B12: Key Financial & Schedule | G12: Master Schedule S-Curve (USD Juta) | M12: Risk Register - Risiko Aktif | R12: Legenda Top Risk (C1-C4)
B13: Cost Performance Index (CPI) | E13: =Input_Bulanan!D12 -> 5 | G13: Planned Value (PV) | J13: =Input_Bulanan!D8 -> 500 | M13: High | P13: =Input_Bulanan!D52 -> 5 | R13: =Input_Bulanan!C75 -> C1 | S13: =Input_Bulanan!D75&" | L="&Input_Bulanan!F75&", C="&Input_Bulanan!G75&", Skala="&Input_Bulanan!H75&" -> "&Input_Bulanan!I75 -> Salt Supply Disruption (gangguan pasokan garam industri) | L=4, C=5, Skala=24 -> High
B14: Schedule Performance Index (SPI) | E14: =Input_Bulanan!D14 -> 1 | G14: Earned Value (EV) | J14: =Input_Bulanan!D9 -> 500 | M14: Moderate to High | P14: =Input_Bulanan!D53 -> 11 | R14: =Input_Bulanan!C76 -> C2 | S14: =Input_Bulanan!D76&" | L="&Input_Bulanan!F76&", C="&Input_Bulanan!G76&", Skala="&Input_Bulanan!H76&" -> "&Input_Bulanan!I76 -> Commissioning Delay (keterlambatan commissioning) | L=5, C=5, Skala=25 -> High
B15: Cost Variance (CV), USD Juta | E15: =Input_Bulanan!D13 -> 400 | G15: Actual Cost (AC) | J15: =Input_Bulanan!D10 -> 100 | M15: Moderate | P15: =Input_Bulanan!D54 -> 18 | R15: =Input_Bulanan!C77 -> C3 | S15: =Input_Bulanan!D77&" | L="&Input_Bulanan!F77&", C="&Input_Bulanan!G77&", Skala="&Input_Bulanan!H77&" -> "&Input_Bulanan!I77 -> EPC Interface Issue (isu EPC interface lintas kontraktor) | L=4, C=4, Skala=19 -> Moderate to High
B16: Schedule Variance (SV), USD Juta | E16: =Input_Bulanan!D15 -> 0 | G16: (Bar proporsional: lihat conditional formatting / grafik pada versi HTML) | M16: Low to Moderate | P16: =Input_Bulanan!D55 -> 4 | R16: =Input_Bulanan!C78 -> C4 | S16: =Input_Bulanan!D78&" | L="&Input_Bulanan!F78&", C="&Input_Bulanan!G78&", Skala="&Input_Bulanan!H78&" -> "&Input_Bulanan!I78 -> Long Lead Equipment (keterlambatan peralatan utama) | L=3, C=3, Skala=13 -> Moderate
M17: Low | P17: =Input_Bulanan!D56 -> 3
M18: Total Risiko Aktif | P18: =Input_Bulanan!D57 -> 41
B20: Catatan Metodologi | M20: Mitigation Health Progress
M21: Completed Mitigations | P21: =Input_Bulanan!D60 -> 0.82
M22: On Track Mitigations | P22: =Input_Bulanan!D61 -> 0.18
M23: Overdue Actions | P23: =Input_Bulanan!D62 -> 0.76
M24: Need Escalation (jumlah aksi) | P24: =Input_Bulanan!D63 -> 5
B26: PANEL C - EARLY WARNING SYSTEM (EWS) ALERTS
B27: Parameter | G27: Threshold | K27: Aktual | M27: Aman | N27: Waspada | O27: Bahaya | P27: Implikasi Operasional & Finansial
B28: =Input_Bulanan!C67 -> First Shipment | G28: =Input_Bulanan!D67 -> Target (Threshold) | K28: =TEXT(Input_Bulanan!E67,"dd-mmm-yy") -> 01-Apr-26 | M28: =IF(Input_Bulanan!H67="Aman","V","") -> V | N28: =IF(Input_Bulanan!H67="Waspada","V","") | O28: =IF(Input_Bulanan!H67="Bahaya","V","") | P28: Keterlambatan pengiriman pertama berpotensi memicu klaim dari Offtaker utama.
B29: =Input_Bulanan!C68 -> Project Progress | G29: =Input_Bulanan!D68 -> Minimal 80% | K29: =TEXT(Input_Bulanan!E68,"0%") -> 88% | M29: =IF(Input_Bulanan!H68="Aman","V","") | N29: =IF(Input_Bulanan!H68="Waspada","V","") | O29: =IF(Input_Bulanan!H68="Bahaya","V","") -> V | P29: Keterlambatan progres berpotensi menunda tahap commissioning.
B30: =Input_Bulanan!C69 -> Offtaker Agreement | G30: =Input_Bulanan!D69 -> SPI >= 1,00 | K30: =TEXT(Input_Bulanan!E69,"0%") -> 60% | M30: =IF(Input_Bulanan!H69="Aman","V","") | N30: =IF(Input_Bulanan!H69="Waspada","V","") | O30: =IF(Input_Bulanan!H69="Bahaya","V","") -> V | P30: Belum tercapainya kuota offtake minimal mengancam kelayakan finansial operasi.
B35: PANEL D - EXECUTIVE ACTIONS & DECISION REQUIRED
B36: ="Prioritas 1—2: [1] " & INDEX(Risk_Action_Tracker!E$6:E$15, MATCH(LARGE(Risk_Action_Tracker!Z$6:Z$15, 1), Risk_Action_Tracker!Z$6:Z$15, 0)) & " · [2] " & INDEX(Risk_Action_Tracker!E$6:E$15, MATCH(LARGE(Risk_Action_Tracker!Z$6:Z$15, 2), Risk_Action_Tracker!Z$6:Z$15, 0)) -> Prioritas 1—2: [1] Mengesahkan pembentukan tim Interface Coordinator dan menerapkan Interface Management Plan (IMP) yang mengikat seluruh kontraktor; mengharuskan Rekind menyelaraskan jadwal penyusunan gambar detail dengan kemajuan ISBL EPC-A. · [2] Memberikan dispensasi perpanjangan jaminan pelaksanaan secara terkendali; meminta Parent Company Guarantee dari PT Perusahaan Induk X (Persero) untuk menjamin ketersediaan pendanaan bila Rekind menghadapi kendala likuiditas.
B37: Rincian lengkap: lihat sheet 'Risk_Action_Tracker' - Executive Action Tracker Direksi/PSC.

Sheet Referensi_Threshold
A2: REFERENSI FORMULA & AMBANG BATAS (THRESHOLD) — PROJECT RISK & HEALTH DASHBOARD
A3: Proyek X Project Perusahaan X | Sumber: Standarisasi Eksekutif Project Risk & Health Dashboard (Studi Kelayakan Deloitte; Risk Register Proyek X 2025) & Benchmark PT Pertamina (Persero) - Direktorat Manajemen Risiko / Permen BUMN No.02/2023
A5: 1. LIMA PILAR KESEHATAN PROYEK (PROJECT HEALTH) & FORMULA
A6: Pilar | B6: Indikator Utama | C6: Formula | D6: Bobot dalam PHS | E6: Sumber / Referensi
A7: Financial Health | B7: Cost Performance Index (CPI) Cost Variance (CV) | C7: CPI = EV / AC CV = EV - AC | D7: 20% | E7: Earned Value Management (EVM) - PMI Standard; ScheduleReader.com, 'Managing Project Health with SPI & CPI'
A8: Schedule Health | B8: Schedule Performance Index (SPI) Schedule Variance (SV) | C8: SPI = EV / PV SV = EV - PV | D8: 0.2 | E8: Earned Value Management (EVM) - PMI Standard; ScheduleReader.com
A9: Supply Readiness Index (SRI) | B9: 5 parameter tertimbang pasokan (supply chain) | C9: SRI = S (Wi x Si) | D9: 0.2 | E9: Risk Register Proyek X - Pengelompokan Tahapan Pekerjaan Proyek (2025)
A10: Project Execution Index (PEI) | B10: 4 parameter tertimbang pelaksanaan EPC | C10: PEI = S (Pj x Wj) | D10: 0.2 | E10: Risk Register Proyek X 2025; praktik EPC Progress-S-Curve industri
A11: Commercial Readiness Index (CRI) | B11: 5 parameter tertimbang kesiapan komersial | C11: CRI = S (Wk x Sk) | D11: 0.2 | E11: Risk Register Proyek X 2025
A13: Overall Project Health Score (PHS)
A14: PHS = (FinancialScore x 0,20) + (ScheduleScore x 0,20) + (SRI x 0,20) + (PEI x 0,20) + (CRI x 0,20)
A15: Catatan: FinancialScore & ScheduleScore dikonversi dari CPI/SPI. Jika indeks >= 1,00, skor = 100 (maksimal). Jika < 1,00, skor = indeks x 100.
A17: 2. PARAMETER & BOBOT SUPPLY READINESS INDEX (SRI)
A18: Parameter | B18: Bobot | C18: Deskripsi
A19: Salt Contract | B19: 0.25 | C19: Kepastian kontrak pasokan bahan baku garam industri jangka panjang dengan PT Garam maupun pemasok luar negeri.
A20: Salt Inventory | B20: 0.2 | C20: Kesiapan & kapasitas operasional gudang penyimpanan garam di pelabuhan dan lokasi pabrik.
A21: Supplier Qualification | B21: 0.2 | C21: Tingkat pemenuhan kualifikasi teknis dan standar kualitas garam dari para calon pemasok.
A22: Shipping Readiness | B22: 0.2 | C22: Kesiapan fasilitas pelabuhan, ketersediaan armada kapal logistik, dan jalur bongkar muat garam.
A23: Utility Readiness | B23: 0.15 | C23: Jaminan kesiapan tie-in pasokan gas bumi dari SKK Migas, air proses, uap panas, dan ketersediaan daya listrik.
A25: 3. PARAMETER & BOBOT PROJECT EXECUTION INDEX (PEI)
A26: Parameter | B26: Bobot | C26: Deskripsi
A27: Engineering Progress | B27: 0.25 | C27: Persentase penyelesaian gambar kerja detail (DED), dokumen spesifikasi teknis, dan persetujuan vendor drawings.
A28: Procurement Progress | B28: 0.3 | C28: Kemajuan pengadaan barang, khususnya long lead items (menara karbonasi, kiln dekomposisi, reaktor utama).
A29: Construction Progress | B29: 0.35 | C29: Kemajuan fisik konstruksi sipil, pondasi alat berat, struktur baja, instalasi mekanikal, kelistrikan, pemipaan.
A30: Commissioning Preparation | B30: 0.1 | C30: Penyelesaian dokumen prosedur pengujian, tim start-up, Loop Test instrumen, dan suku cadang awal operasional.
A32: 4. PARAMETER & BOBOT COMMERCIAL READINESS INDEX (CRI)
A33: Parameter | B33: Bobot | C33: Deskripsi
A34: Offtake Agreement | B34: 0.2 | C34: Jumlah volume produk yang telah terikat dalam nota kesepahaman (MOU/Offtake Agreement) dengan pembeli domestik.
A35: Marketing Strategy | B35: 0.2 | C35: Kesiapan strategi penetapan harga kompetitif terhadap produk impor dan diversifikasi varian produk.
A36: Distribution Readiness | B36: 0.15 | C36: Kesiapan logistik pengiriman produk akhir: bagging unit, armada pengangkutan darat, konveyor pelabuhan.
A37: Operation Team Ready | B37: 0.2 | C37: Kesiapan tim operasi pabrik: sertifikasi operator, SOP pengoperasian, pelatihan simulasi kondisi darurat.
A38: Product Qualification | B38: 0.25 | C38: Kesiapan laboratorium pengujian mutu produk & sertifikasi SNI agar memenuhi kualifikasi industri premium.
A40: 5. TABEL BATAS TOLERANSI (THRESHOLD) - SISTEM RAG (RED-AMBER-GREEN)
A41: Pilar Kesehatan | B41: Indikator | C41: Hijau | D41: Kuning | E41: Oranye | F41: Merah
A42: Financial Health | B42: CPI | C42: CPI >= 1,00 | D42: 0,95-0,99 | E42: 0,90-0,94 | F42: CPI < 0,90
A43: Schedule Health | B43: SPI | C43: SPI >= 1,00 | D43: 0,95-0,99 | E43: 0,90-0,94 | F43: SPI < 0,90
A44: Supply Readiness | B44: SRI | C44: SRI >= 90% | D44: 75-89% | E44: 65-74% | F44: SRI < 65%
A45: Project Execution | B45: Deviasi Fisik | C45: <= 4% | D45: 4,1-6% | E45: 6,1-10% | F45: > 10%
A46: Commercial Readiness | B46: CRI | C46: CRI >= 80% | D46: 60-79% | E46: 50-59% | F46: CRI < 50%
A47: Overall Health | B47: PHS | C47: 90-100% | D47: 75-89% | E47: 60-74% | F47: < 60%
A49: 6. KRITERIA LIKELIHOOD (PROBABILITAS) - MATRIKS RISIKO 5x5
A50: Catatan: kriteria berikut merupakan kriteria standar manajemen risiko (ISO 31000 & benchmark Pertamina RCSA/KRI). Sesuaikan dengan Pedoman Manajemen Risiko Perusahaan X resmi apabila tersedia angka baku internal.
A51: Level (L) | B51: Kategori | C51: Kriteria Probabilitas Kejadian
A52: 1 | B52: Sangat Jarang Terjadi | C52: Kemungkinan terjadi < 10% selama siklus proyek; belum pernah terjadi pada proyek sejenis.
A53: 2 | B53: Jarang Terjadi | C53: Kemungkinan terjadi 10-30%; pernah terjadi namun jarang pada proyek EPC sejenis.
A54: 3 | B54: Bisa Terjadi | C54: Kemungkinan terjadi 30-50%; pernah terjadi beberapa kali pada proyek sejenis.
A55: 4 | B55: Sangat Mungkin Terjadi | C55: Kemungkinan terjadi 50-70%; kondisi/indikasi saat ini mengarah pada terjadinya risiko.
A56: 5 | B56: Hampir Pasti Terjadi | C56: Kemungkinan terjadi > 70%; sudah terdapat indikasi kuat / sedang berlangsung saat ini.
A58: 7. KRITERIA CONSEQUENCE (DAMPAK) - MATRIKS RISIKO 5x5
A59: Level (C) | B59: Kategori | C59: Kriteria Dampak (Finansial / Jadwal / Reputasi)
A60: 1 | B60: Sangat Rendah | C60: Dampak biaya < USD 0,5 Juta; keterlambatan jadwal < 1 minggu; tanpa dampak reputasi/K3.
A61: 2 | B61: Rendah | C61: Dampak biaya USD 0,5-2 Juta; keterlambatan jadwal 1-4 minggu; keluhan internal, dapat dikelola PIC.
A62: 3 | B62: Moderat | C62: Dampak biaya USD 2-10 Juta; keterlambatan jadwal 1-2 bulan; perhatian manajemen menengah/PSC.
A63: 4 | B63: Tinggi | C63: Dampak biaya USD 10-30 Juta; keterlambatan jadwal 2-6 bulan; berisiko pada target COD & perhatian Direksi.
A64: 5 | B64: Sangat Tinggi | C64: Dampak biaya > USD 30 Juta; keterlambatan > 6 bulan atau mengancam kegagalan COD; berdampak pada kelayakan NPV proyek & reputasi korporat.
A66: 8. KLASIFIKASI LEVEL RISIKO - 5 TINGKAT (Pedoman Manajemen Risiko Perusahaan X)
A67: Skor Matriks L x C TIDAK lagi dihitung dari perkalian langsung L x C dengan pembagian rentang rata, melainkan menggunakan Tabel Skala Risiko Non-Linear (Skala 1-25) pada bagian 10 di bawah, yang memprioritaskan bobot Consequence (Dampak) dibanding Likelihood (Probabilitas) untuk kombinasi bernilai sama — konsisten dengan pendekatan penentuan level risiko non-linear yang lazim digunakan pada matriks 5x5 ISO 31000:2018 / AS-NZS ISO 31000 dan praktik matriks risiko K3/SMKP BUMN sektor energi-tambang (rujukan pola: Kepdirjen Minerba No.1827.K/30/MEM/2018). Overall Risk Index (skala 0-100, benchmark Pertamina) tetap memakai rentang rata seperti semula.
A68: Level Risiko | B68: Skor Matriks L x C (1-25) | C68: Overall Risk Index (0-100)
A69: Low | B69: 1 - 5 | C69: 0 - 20
A70: Low to Moderate | B70: 6 - 11 | C70: 21 - 40
A71: Moderate | B71: 12 - 15 | C71: 41 - 60
A72: Moderate to High | B72: 16 - 19 | C72: 61 - 80
A73: High | B73: 20 - 25 | C73: 81 - 100
A75: 9. KOMPOSISI SUB-INDEKS OVERALL RISK INDEX (BENCHMARK PERTAMINA)
A76: Supply Risk Index | B76: 0.4 | C76: Bahan baku garam industri, kualitas garam lokal vs impor, keandalan pemasok, risiko logistik maritim, kesiapan gudang, kesiapan utilitas.
A77: Execution Risk Index | B77: 0.4 | C77: Kesiapan rekayasa desain, pengadaan peralatan utama, produktivitas tenaga kerja, antarmuka antar-EPC, pengapalan long lead items, kesiapan uji fungsi.
A78: Commercial Risk Index | B78: 0.2 | C78: Pengikatan kontrak offtake, fluktuasi harga Proyek X global, tekanan produk impor, kesiapan logistik distribusi hilir, sertifikasi kualitas produk.
A79: Overall Risk Index = (Supply Risk Index x 0,40) + (Execution Risk Index x 0,40) + (Commercial Risk Index x 0,20)
A81: Sumber benchmark tata kelola risiko: PT Pertamina (Persero) - Direktorat Manajemen Risiko (2nd Line of Defense, Permen BUMN No.02/2023), Komite Tata Kelola Terintegrasi (KTKT), Gate Review/FID, RCSA, KRI, ICT, C-RBDD; PT Biro Klasifikasi Indonesia (Persero) - SK-6/2023 (Risk Appetite berbasis Net Working Capital); klasifikasi 5-tingkat Low/Low to Moderate/Moderate/Moderate to High/High mengikuti nomenklatur Pedoman Manajemen Risiko Perusahaan X.
A86: 10. TABEL SKALA RISIKO (RISK RANKING) 5x5 NON-LINEAR & WARNA HEAT MAP
A87: Tabel skala risiko berikut menetapkan urutan (rank) 1-25 untuk setiap 25 kombinasi Likelihood (L) x Consequence (C) sesuai spesifikasi metodologi risiko internal yang ditetapkan Project Control Proyek X Perusahaan X. Berbeda dari perkalian L x C sederhana, urutan ini memberi bobot lebih besar pada Consequence saat terjadi nilai sama, mengikuti kaidah umum non-linear risk ranking pada standar ISO 31000:2018 dan praktik matriks risiko korporasi BUMN. Skala menentukan posisi & warna sel pada Risk Profile Heat Map di sheet Dashboard.
A89: Key (L x10 + C) | B89: L (1-5) | C89: C (1-5) | D89: Skala (1-25) | E89: Level Risiko | F89: Kode Warna (Hex)
A90: 11 | B90: 1 | C90: 1 | D90: 1 | E90: Low | F90: #538135
A91: 21 | B91: 2 | C91: 1 | D91: 2 | E91: Low | F91: #538135
A92: 31 | B92: 3 | C92: 1 | D92: 3 | E92: Low | F92: #538135
A93: 41 | B93: 4 | C93: 1 | D93: 4 | E93: Low | F93: #538135
A94: 12 | B94: 1 | C94: 2 | D94: 5 | E94: Low | F94: #538135
A95: 22 | B95: 2 | C95: 2 | D95: 6 | E95: Low to Moderate | F95: #A9D18E
A96: 51 | B96: 5 | C96: 1 | D96: 7 | E96: Low to Moderate | F96: #A9D18E
A97: 32 | B97: 3 | C97: 2 | D97: 8 | E97: Low to Moderate | F97: #A9D18E
A98: 42 | B98: 4 | C98: 2 | D98: 9 | E98: Low to Moderate | F98: #A9D18E
A99: 13 | B99: 1 | C99: 3 | D99: 10 | E99: Low to Moderate | F99: #A9D18E
A100: 23 | B100: 2 | C100: 3 | D100: 11 | E100: Low to Moderate | F100: #A9D18E
A101: 52 | B101: 5 | C101: 2 | D101: 12 | E101: Moderate | F101: #FFD966
... A114: 55 | B114: 5 | C114: 5 | D114: 25 | E114: High | F114: #E06666
A116: Sumber/Referensi Tabel Skala: metodologi non-linear risk ranking ISO 31000:2018 (klausul 5.4.3 - penentuan level risiko); praktik matriks 5x5 K3/SMKP BUMN sektor energi & tambang; disesuaikan dengan nomenklatur 5-tingkat Pedoman Manajemen Risiko Perusahaan X (Low / Low to Moderate / Moderate / Moderate to High / High).
A118: 11. METODOLOGI EARLY WARNING SYSTEM (EWS) — 3 STATUS (AMAN / WASPADA / BAHAYA)
A119: Setiap parameter EWS diklasifikasikan ke 3 status menggunakan pendekatan Key Risk Indicator (KRI) Traffic Light dengan buffer toleransi 10% dari threshold sebagai batas Waspada (Amber Zone), mengacu pada COSO Enterprise Risk Management Framework (2017) dan praktik RCSA-KRI PT Pertamina (Persero) yang telah dirujuk pada dokumen ini.
A121: Status | B121: Definisi Ambang Batas (untuk indikator "semakin tinggi semakin baik") | E121: Warna
A122: Aman | B122: Nilai Aktual >= Threshold (100% dari batas aman)
A123: Waspada | B123: Threshold x 90% <= Nilai Aktual < Threshold
A124: Bahaya | B124: Nilai Aktual < Threshold x 90%
A127: 12. METODOLOGI PERHITUNGAN SUB-INDEKS RISIKO
A129: Masing-masing sub-indeks risiko dihitung melalui metode penilaian pakar (expert scoring) pada skala 0-100:
A130: Sub-Indeks | B130: Definisi | C130: Parameter Penilaian | D130: Skala | E130: Skor 0 (Terendah) | F130: Skor 100 (Tertinggi)
A131: Supply Risk Index | B131: Mengukur tingkat risiko rantai pasokan bahan baku proyek | C131: Ketersediaan kontrak garam jangka panjang, stabilitas harga, keandalan pemasok, kapasitas logistik & pelabuhan, regulasi impor garam (Perpres 17/2025) | D131: 0 – 100 | E131: Risiko sangat rendah (pasokan sepenuhnya terjamin) | F131: Risiko sangat tinggi (pasokan tidak tersedia)
A132: Execution Risk Index | B132: Mengukur tingkat risiko pelaksanaan proyek EPC | C132: Progres konstruksi vs jadwal, performa kontraktor, isu interface antar EPC packages, kesiapan commissioning, ketersediaan sumber daya, kendala perizinan | D132: 0 – 100 | E132: Risiko sangat rendah (eksekusi sempurna) | F132: Risiko sangat tinggi (proyek terhenti)
A133: Commercial Risk Index | B133: Mengukur tingkat risiko komersial & pemasaran produk Proyek X | C133: Offtake agreement, strategi pemasaran, kesiapan distribusi, kualifikasi produk, persaingan impor | D133: 0 – 100 | E133: Risiko sangat rendah (pasar terjamin) | F133: Risiko sangat tinggi (pasar tidak tersedia)
A136: Formula Overall Risk Index = (Supply Risk Index × 0,4) + (Execution Risk Index × 0,4) + (Commercial Risk Index × 0,2)
A139: 13. KLASIFIKASI JUMLAH REGISTER RISIKO AKTIF (5 TINGKAT Perusahaan X)
...

Sheet Input_Bulanan
C2: INPUT DATA BULANAN — DIISI OLEH PIC / PROJECT CONTROL SETIAP PERIODE PELAPORAN
C3: Sel KUNING (font biru) = input manual. Sel ABU-ABU = formula otomatis, jangan diubah manual. Arahkan kursor ke label bertanda (i) untuk penjelasan parameter.
C4: Nama Perusahaan | D4: =Config!B6 -> Test | F4: Nama Proyek | G4: =Config!B7 -> Satu
C5: Periode Pelaporan (Bulan/Tahun) | D5: 46327 | E5: Status Dokumen | F5: Final
C7: 1. EARNED VALUE MANAGEMENT (EVM) — FINANCIAL & SCHEDULE HEALTH (satuan: USD Juta, kumulatif)
C8: Planned Value (PV) — kumulatif s.d. periode ini | D8: 500 | E8: NPV
C9: Earned Value (EV) — kumulatif s.d. periode ini | D9: 500
C10: Actual Cost (AC) — kumulatif s.d. periode ini | D10: 100
C11: Net Present Value (NPV) — USD Juta | D11: 77.6
C12: Cost Performance Index (CPI = EV/AC) | D12: =D9/D10 -> 5
C13: Cost Variance (CV = EV-AC), USD Juta | D13: =D9-D10 -> 400
C14: Schedule Performance Index (SPI = EV/PV) | D14: =D9/D8 -> 1
C15: Schedule Variance (SV = EV-PV), USD Juta | D15: =D9-D8 -> 0
C17: 2. SUPPLY READINESS INDEX (SRI) — skor kesiapan tiap parameter
C18: Salt Contract | D18: 0.82 | E18: =Referensi_Threshold!B19 -> 0.25 | F18: =D18*E18 -> 0.205
C19: Salt Inventory | D19: 0.8 | E19: =Referensi_Threshold!B20 -> 0.2 | F19: =D19*E19 -> 0.16
C20: Supplier Qualification | D20: 0.75 | E20: =Referensi_Threshold!B21 -> 0.2 | F20: =D20*E20 -> 0.15
C21: Shipping Readiness | D21: 0.85 | E21: =Referensi_Threshold!B22 -> 0.2 | F21: =D21*E21 -> 0.17
C22: Utility Readiness | D22: 0.8 | E22: =Referensi_Threshold!B23 -> 0.15 | F22: =D22*E22 -> 0.12
C23: Salt Readiness | D23: 0.8 | E23: =Referensi_Threshold!B24 -> 0 | F23: =D23*E23 -> 0
C24: SRI — Supply Readiness Index (tertimbang) | D24: =F24 -> 0.805 | E24: =SUM(E18:E23) -> 1 | F24: =SUM(F18:F23) -> 0.805
C26: 3. PROJECT EXECUTION INDEX (PEI) — progres aktual tiap parameter
C27: Engineering Progress | D27: 0.88 | E27: =Referensi_Threshold!B27 -> 0.25 | F27: =D27*E27 -> 0.22
C28: Procurement Progress | D28: 0.73 | E28: =Referensi_Threshold!B28 -> 0.3 | F28: =D28*E28 -> 0.219
C29: Construction Progress | D29: 0.82 | E29: =Referensi_Threshold!B29 -> 0.35 | F29: =D29*E29 -> 0.287
C30: Commissioning Preparation | D30: 0.42 | E30: =Referensi_Threshold!B30 -> 0.1 | F30: =D30*E30 -> 0.042
C31: Pencapaian Performance Test | D31: 0.4 | E31: =Referensi_Threshold!B31 -> 0 | F31: =D31*E31 -> 0
C32: PEI — Project Execution Index (tertimbang) | D32: =F32 -> 0.768 | E32: =SUM(E27:E31) -> 1 | F32: =SUM(F27:F31) -> 0.768
C33: Deviasi Kemajuan Fisik vs Target (S-Curve) | D33: 0.058
C35: 4. COMMERCIAL READINESS INDEX (CRI) — skor kesiapan tiap parameter
C36: Offtake Agreement | D36: 0.6 | E36: =Referensi_Threshold!B34 -> 0.2 | F36: =D36*E36 -> 0.12
C37: Marketing Strategy | D37: 0.6 | E37: =Referensi_Threshold!B35 -> 0.2 | F37: =D37*E37 -> 0.12
C38: Distribution Readiness | D38: 0.8 | E38: =Referensi_Threshold!B36 -> 0.15 | F38: =D38*E38 -> 0.12
C39: Operation Team Ready | D39: 0.8 | E39: =Referensi_Threshold!B37 -> 0.2 | F39: =D39*E39 -> 0.16
C40: Product Qualification | D40: 0.4 | E40: =Referensi_Threshold!B38 -> 0.25 | F40: =D40*E40 -> 0.1
C41: Regulatory Readiness | D41: 0.5 | E41: =Referensi_Threshold!B39 -> 0 | F41: =D41*E41 -> 0
C42: CRI — Commercial Readiness Index (tertimbang) | D42: =F42 -> 0.62 | E42: =SUM(E36:E41) -> 1 | F42: =SUM(F36:F41) -> 0.62
C44: 5. OVERALL RISK INDEX — sub-indeks risiko (skor 0-100, benchmark Pertamina)
C45: Supply Risk Index (bobot 40%) | D45: =D24*100 -> 80.5 | E45: =Config!B21 -> 0.4
C46: Execution Risk Index (bobot 40%) | D46: =D32*100 -> 76.8 | E46: =Config!B22 -> 0.4
C47: Commercial Risk Index (bobot 20%) | D47: =D42*100 -> 62 | E47: =Config!B23 -> 0.2
C48: Overall Risk Index (tertimbang, skala 0-100) | D48: =(D45*E45)+(D46*E46)+(D47*E47) -> 75.32
C49: Overall Risk Level (5 Tingkat, formula) | D49: =IF(D48<=20,"Low",IF(D48<=44,"Low to Moderate",IF(D48<=60,"Moderate",IF(D48<=76,"Moderate to High","High")))) -> Moderate to High
C51: 6. REGISTER RISIKO AKTIF — Jumlah Risiko per 5 Tingkat Perusahaan X
C52: High | D52: 5
C53: Moderate to High | D53: 11
C54: Moderate | D54: 18
C55: Low to Moderate | D55: 4
C56: Low | D56: 3
C57: Total Risiko Aktif | D57: =SUM(D52:D56) -> 41
C59: 7. STATUS MITIGASI & DINAMIKA PERGERAKAN RISIKO (BULAN BERJALAN)
C60: Completed Mitigations (%) | D60: 0.82 | E60: Risiko Baru (New Risk) | F60: 2
C61: Overdue Actions (%) | D61: 0.18 | E61: Risiko Eskalasi (Escalated Risk) | F61: 3
C62: On Track Mitigations (%) | D62: 0.76 | E62: Risiko Menurun (Reduced Risk) | F62: 5
C63: Need Escalation (jumlah aksi) | D63: 5 | E63: Risiko Ditutup (Closed Risk) | F63: 4
C65: 8. EARLY WARNING SYSTEM (EWS) — NILAI AKTUAL PEMANTAUAN
C66: Parameter EWS | D66: Threshold (Batas Aman) | E66: Nilai Aktual | F66: Nilai Threshold (Numerik) | G66: Buffer Waspada (90%) | H66: Status EWS (3 Level)
C67: First Shipment | D67: Target (Threshold) | E67: 46113 | F67: 46096 | G67: hari | H67: =IF(E67>=F67,"Aman",IF(E67>=G67,"Waspada","Bahaya")) -> Aman
C68: Project Progress | D68: Minimal 80% | E68: 0.88 | F68: 0.9 | G68: % | H68: =IF(E68>=F68,"Aman",IF(E68>=G68,"Waspada","Bahaya")) -> Bahaya
C69: Offtaker Agreement | D69: SPI >= 1,00 | E69: 0.6 | F69: 0.7 | G69: % | H69: =IF(E69>=F69,"Aman",IF(E69>=G69,"Waspada","Bahaya")) -> Bahaya
C72: 9. TOP RISK REGISTER (C1-C4) — INPUT LIKELIHOOD (L) & CONSEQUENCE (C) UNTUK HEAT MAP
C73: Skala Risiko & Risk Level dihitung otomatis dari Tabel Skala Risiko Non-Linear 5x5 pada sheet Referensi_Threshold bagian 10 (bukan lagi perkalian L x C sederhana). Posisi pada Risk Profile Heat Map di sheet Dashboard mengikuti nilai L & C ini secara otomatis.
C74: Kode | D74: Deskripsi Risiko Utama | E74: Kategori | F74: L (1-5) | G74: C (1-5) | H74: Score | I74: Risk Level
C75: C1 | D75: Salt Supply Disruption (gangguan pasokan garam industri) | E75: Hulu / Supply | F75: 4 | G75: 5 | H75: =INDEX(Referensi_Threshold!$D$90:$D$114,MATCH(F75*10+G75,Referensi_Threshold!$A$90:$A$114,0)) -> 24 | I75: =INDEX(Referensi_Threshold!$E$90:$E$114,MATCH(F75*10+G75,Referensi_Threshold!$A$90:$A$114,0)) -> High
C76: C2 | D76: Commissioning Delay (keterlambatan commissioning) | E76: Eksekusi | F76: 5 | G76: 5 | H76: =INDEX(Referensi_Threshold!$D$90:$D$114,MATCH(F76*10+G76,Referensi_Threshold!$A$90:$A$114,0)) -> 25 | I76: =INDEX(Referensi_Threshold!$E$90:$E$114,MATCH(F76*10+G76,Referensi_Threshold!$A$90:$A$114,0)) -> High
C77: C3 | D77: EPC Interface Issue (isu EPC interface lintas kontraktor) | E77: Eksekusi | F77: 4 | G77: 4 | H77: =INDEX(Referensi_Threshold!$D$90:$D$114,MATCH(F77*10+G77,Referensi_Threshold!$A$90:$A$114,0)) -> 19 | I77: =INDEX(Referensi_Threshold!$E$90:$E$114,MATCH(F77*10+G77,Referensi_Threshold!$A$90:$A$114,0)) -> Moderate to High
C78: C4 | D78: Long Lead Equipment (keterlambatan peralatan utama) | E78: Pengadaan | F78: 3 | G78: 3 | H78: =INDEX(Referensi_Threshold!$D$90:$D$114,MATCH(F78*10+G78,Referensi_Threshold!$A$90:$A$114,0)) -> 13 | I78: =INDEX(Referensi_Threshold!$E$90:$E$114,MATCH(F78*10+G78,Referensi_Threshold!$A$90:$A$114,0)) -> Moderate

Sheet Risk_Action_Tracker
B2: EXECUTIVE ACTION TRACKER — DIREKSI / PROJECT STEERING COMMITTEE (PSC)
B3: Proyek X Project Perusahaan X — diperbarui setiap periode pelaporan bulanan. Kategori Level mengikuti klasifikasi 5-tingkat Pedoman Manajemen Risiko Perusahaan X.
B5: No | C5: Isu Strategis / Peristiwa Risiko Kritis | D5: Kategori & Level Risiko | E5: Keputusan & Rencana Tindakan Diperlukan | F5: PIC (Unit Penanggung Jawab) | G5: Perkiraan Dampak Finansial & Kelayakan NPV | H5: Prioritas Dashboard (1, 2, 3...) | Z5: Helper Priority Score
B6: 1 | C6: Ketergantungan Antarmuka (Interface) Lintas EPC-A, B, C, D | D6: Eksekusi — High | E6: Mengesahkan pembentukan tim Interface Coordinator dan menerapkan Interface Management Plan (IMP) yang mengikat seluruh kontraktor; mengharuskan Rekind menyelaraskan jadwal penyusunan gambar detail dengan kemajuan ISBL EPC-A. | F6: VP Proyek Proyek X & SVP Pengembangan Portofolio | G6: Mencegah kegagalan penyelesaian proyek bersamaan, mengamankan target COD Maret 2028, melindungi NPV sebesar USD 77,60 Juta. | H6: 1 | Z6: =IF(D6="","", IF(ISNUMBER(SEARCH("Moderate to High", D6)), 40, IF(ISNUMBER(SEARCH("High", D6)), 50, IF(ISNUMBER(SEARCH("Low to Moderate", D6)), 20, IF(ISNUMBER(SEARCH("Moderate", D6)), 30, 10)))) + (1/ROW())) -> 50.166667
B7: 2 | C7: Keterbatasan Kapasitas Keuangan Rekind (EPC-B) | D7: Finansial — Moderate to High | E7: Memberikan dispensasi perpanjangan jaminan pelaksanaan secara terkendali; meminta Parent Company Guarantee dari PT Perusahaan Induk X (Persero) untuk menjamin ketersediaan pendanaan bila Rekind menghadapi kendala likuiditas. | F7: Direktur Utama Perusahaan X & SVP Keuangan | G7: Melindungi penyelesaian gardu kelistrikan dan fasilitas tie-in, menghindari denda klaim tambahan dari EPC-A. | H7: 2 | Z7: =IF(D7="","", IF(ISNUMBER(SEARCH("Moderate to High", D7)), 40, IF(ISNUMBER(SEARCH("High", D7)), 50, IF(ISNUMBER(SEARCH("Low to Moderate", D7)), 20, IF(ISNUMBER(SEARCH("Moderate", D7)), 30, 10)))) + (1/ROW())) -> 40.142857
B8: 3 | C8: Kelangkaan & Hambatan Perizinan Impor Garam Industri | D8: Hulu / Supply — Moderate to High | E8: Lobi aktif dan koordinasi dengan Kementerian Perindustrian serta Kementerian Kelautan dan Perikanan guna mengamankan alokasi kuota impor tahunan setahun sebelum operasional dimulai, merujuk Perpres No.17/2025. | F8: Direktur Utama Perusahaan X & SVP Pengembangan Portofolio | G8: Menghindari penghentian operasional akibat kekosongan bahan baku; menghemat potensi kerugian EBITDA Rp 137 Miliar/kuartal. | H8: 3 | Z8: =IF(D8="","", IF(ISNUMBER(SEARCH("Moderate to High", D8)), 40, IF(ISNUMBER(SEARCH("High", D8)), 50, IF(ISNUMBER(SEARCH("Low to Moderate", D8)), 20, IF(ISNUMBER(SEARCH("Moderate", D8)), 30, 10)))) + (1/ROW())) -> 40.125
B9: 4 | C9: Fluktuasi Nilai Tukar Valas Terhadap Sisa Pembayaran Kontrak EPC-A | D9: Keuangan — Moderate | E9: Menginstruksikan Kompartemen Keuangan mengimplementasikan strategi hedging valas (forward/opsi) bekerja sama dengan bank BUMN nasional untuk mengunci porsi sisa pembayaran dalam USD. | F9: Direktur Keuangan Perusahaan X | G9: Mengeliminasi risiko pembengkakan biaya investasi riil akibat depresiasi rupiah; mengamankan ambang batas investasi USD 297,67 Juta. | H9: 4 | Z9: =IF(D9="","", IF(ISNUMBER(SEARCH("Moderate to High", D9)), 40, IF(ISNUMBER(SEARCH("High", D9)), 50, IF(ISNUMBER(SEARCH("Low to Moderate", D9)), 20, IF(ISNUMBER(SEARCH("Moderate", D9)), 30, 10)))) + (1/ROW())) -> 30.111111
B10: 5 | C10: Hambatan Penerbitan PBG & SLF di Lahan Tursina Barat | D10: Regulasi — Moderate | E10: Membentuk tim percepatan perizinan internal untuk koordinasi harian dengan DLH Kota X dan Dinas PUPR Provinsi Provinsi X guna mempercepat adendum dokumen lingkungan di lahan sengketa. | F10: VP Hukum & Humas Perusahaan X | G10: Mencegah keterlambatan masa efektif konstruksi fisik; menghemat opportunity cost of capital senilai Rp 500 Juta/bulan. | H10: 5 | Z10: =IF(D10="","", IF(ISNUMBER(SEARCH("Moderate to High", D10)), 40, IF(ISNUMBER(SEARCH("High", D10)), 50, IF(ISNUMBER(SEARCH("Low to Moderate", D10)), 20, IF(ISNUMBER(SEARCH("Moderate", D10)), 30, 10)))) + (1/ROW())) -> 30.1
Z11: =IF(D11="","", IF(ISNUMBER(SEARCH("Moderate to High", D11)), 40, IF(ISNUMBER(SEARCH("High", D11)), 50, IF(ISNUMBER(SEARCH("Low to Moderate", D11)), 20, IF(ISNUMBER(SEARCH("Moderate", D11)), 30, 10)))) + (1/ROW()))
B12: Sumber tata kelola: Risk Register Proyek X 2025; kerangka Gate Review & FID PT Pertamina (Persero); Weighted Project Top Risk (Financial Materiality 40%, Strategic Impact 30%, Life Cycle Phase 15%, Financial Health Impact 10%, Baseline Risk Complexity 5%). Level risiko mengikuti klasifikasi 5-tingkat Pedoman Manajemen Risiko Perusahaan X: Low / Low to Moderate / Moderate / Moderate to High / High. | Z12: =IF(D12="","", IF(ISNUMBER(SEARCH("Moderate to High", D12)), 40, IF(ISNUMBER(SEARCH("High", D12)), 50, IF(ISNUMBER(SEARCH("Low to Moderate", D12)), 20, IF(ISNUMBER(SEARCH("Moderate", D12)), 30, 10)))) + (1/ROW()))
Z13: =IF(D13="","", IF(ISNUMBER(SEARCH("Moderate to High", D13)), 40, IF(ISNUMBER(SEARCH("High", D13)), 50, IF(ISNUMBER(SEARCH("Low to Moderate", D13)), 20, IF(ISNUMBER(SEARCH("Moderate", D13)), 30, 10)))) + (1/ROW()))
Z14: =IF(D14="","", IF(ISNUMBER(SEARCH("Moderate to High", D14)), 40, IF(ISNUMBER(SEARCH("High", D14)), 50, IF(ISNUMBER(SEARCH("Low to Moderate", D14)), 20, IF(ISNUMBER(SEARCH("Moderate", D14)), 30, 10)))) + (1/ROW()))
Z15: =IF(D15="","", IF(ISNUMBER(SEARCH("Moderate to High", D15)), 40, IF(ISNUMBER(SEARCH("High", D15)), 50, IF(ISNUMBER(SEARCH("Low to Moderate", D15)), 20, IF(ISNUMBER(SEARCH("Moderate", D15)), 30, 10)))) + (1/ROW()))
B16: DINAMIKA PERGERAKAN RISIKO (BULAN BERJALAN)
B17: Risiko Baru (New Risk) | C17: =Input_Bulanan!F60 -> 2 | D17: Perubahan tarif pajak masukan impor garam industri; risiko sengketa lahan tambahan di area laydown.
B18: Risiko Eskalasi (Escalated Risk) | C18: =Input_Bulanan!F61 -> 3 | D18: Peningkatan level risiko keterlambatan Rekind akibat kendala arus kas internal.
B19: Risiko Menurun (Reduced Risk) | C19: =Input_Bulanan!F62 -> 5 | D19: Penurunan risiko dampak sosial setelah disepakatinya kuota tenaga kerja lokal.
B20: Risiko Ditutup (Closed Risk) | C20: =Input_Bulanan!F63 -> 4 | D20: Penutupan risiko kelayakan AMDAL seiring diterbitkannya izin adendum lingkungan DLH Bontang.
B22: TOP RISK REGISTER (C1-C4) - DETAIL LIKELIHOOD x CONSEQUENCE
B23: Kode | C23: Deskripsi Risiko | D23: Kategori | E23: L | F23: C | G23: Score / Level
B24: =Input_Bulanan!C75 -> C1 | C24: =Input_Bulanan!D75 -> Salt Supply Disruption (gangguan pasokan garam industri) | D24: =Input_Bulanan!E75 -> Hulu / Supply | E24: =Input_Bulanan!F75 -> 4 | F24: =Input_Bulanan!G75 -> 5 | G24: =Input_Bulanan!H75 & " | " & Input_Bulanan!I75 -> 24 | High
B25: =Input_Bulanan!C76 -> C2 | C25: =Input_Bulanan!D76 -> Commissioning Delay (keterlambatan commissioning) | D25: =Input_Bulanan!E76 -> Eksekusi | E25: =Input_Bulanan!F76 -> 5 | F25: =Input_Bulanan!G76 -> 5 | G25: =Input_Bulanan!H76 & " | " & Input_Bulanan!I76 -> 25 | High
B26: =Input_Bulanan!C77 -> C3 | C26: =Input_Bulanan!D77 -> EPC Interface Issue (isu EPC interface lintas kontraktor) | D26: =Input_Bulanan!E77 -> Eksekusi | E26: =Input_Bulanan!F77 -> 4 | F26: =Input_Bulanan!G77 -> 4 | G26: =Input_Bulanan!H77 & " | " & Input_Bulanan!I77 -> 19 | Moderate to High
B27: =Input_Bulanan!C78 -> C4 | C27: =Input_Bulanan!D78 -> Long Lead Equipment (keterlambatan peralatan utama) | D27: =Input_Bulanan!E78 -> Pengadaan | E27: =Input_Bulanan!F78 -> 3 | F27: =Input_Bulanan!G78 -> 3 | G27: =Input_Bulanan!H78 & " | " & Input_Bulanan!I78 -> 13 | Moderate
